swecc_email_sender/__init__.py
swecc_email_sender/cli.py
swecc_email_sender/core/__init__.py
swecc_email_sender/core/loader.py
swecc_email_sender/core/sender.py
swecc_email_sender/utils/__init__.py
swecc_email_sender/utils/markdown_utils.py
swecc_email_sender-1.0.7.dist-info/METADATA
swecc_email_sender-1.0.7.dist-info/WHEEL
swecc_email_sender-1.0.7.dist-info/entry_points.txt
swecc_email_sender-1.0.7.dist-info/licenses/LICENSE
swecc_email_sender-1.0.7.dist-info/RECORD
