Metadata-Version: 2.4
Name: swecc-email-sender
Version: 1.0.7
Summary: A production-ready email automation library using SendGrid
Project-URL: Homepage, https://github.com/swecc-uw/swecc-email-sender
Project-URL: Documentation, https://github.com/swecc-uw-uw/swecc-email-sender#readme
Project-URL: Repository, https://github.com/swecc-uw-uw/swecc-email-sender.git
Project-URL: Bug Tracker, https://github.com/swecc-uw/swecc-email-sender/issues
Author-email: SWECC <info@swecc.org>
License-Expression: MIT
License-File: LICENSE
Keywords: automation,email,markdown,sendgrid
Classifier: Development Status :: 5 - Production/Stable
Classifier: Intended Audience :: Developers
Classifier: License :: OSI Approved :: MIT License
Classifier: Programming Language :: Python :: 3
Classifier: Programming Language :: Python :: 3.8
Classifier: Programming Language :: Python :: 3.9
Classifier: Programming Language :: Python :: 3.10
Classifier: Programming Language :: Python :: 3.11
Classifier: Topic :: Communications :: Email
Classifier: Topic :: Software Development :: Libraries :: Python Modules
Requires-Python: >=3.8
Requires-Dist: markdown>=3.3.0
Provides-Extra: dev
Requires-Dist: beautifulsoup4>=4.9.0; extra == 'dev'
Requires-Dist: black>=22.0.0; extra == 'dev'
Requires-Dist: flake8>=5.0.0; extra == 'dev'
Requires-Dist: isort>=5.0.0; extra == 'dev'
Requires-Dist: mypy>=1.0.0; extra == 'dev'
Requires-Dist: pre-commit>=3.5.0; extra == 'dev'
Requires-Dist: pytest-cov>=4.0.0; extra == 'dev'
Requires-Dist: pytest>=7.0.0; extra == 'dev'
Requires-Dist: ruff>=0.2.0; extra == 'dev'
